knorket_trustmesh/__init__.py
knorket_trustmesh/ziti_router_auto_enroll.py
knorket_trustmesh-0.3.1.dist-info/METADATA
knorket_trustmesh-0.3.1.dist-info/WHEEL
knorket_trustmesh-0.3.1.dist-info/entry_points.txt
knorket_trustmesh-0.3.1.dist-info/RECORD
